structengpy/__init__.py
structengpy/app/__init__.py
structengpy/app/general/__init__.py
structengpy/app/general/db.py
structengpy/app/general/model.py
structengpy/app/general/orm.py
structengpy/app/general/environment/__init__.py
structengpy/app/general/environment/curve.py
structengpy/app/general/environment/project.py
structengpy/app/general/io/__init__.py
structengpy/app/general/io/dxf.py
structengpy/app/general/io/s2k.py
structengpy/app/general/load/__init__.py
structengpy/app/general/load/loadcase.py
structengpy/app/general/load/pattern.py
structengpy/app/general/object/__init__.py
structengpy/app/general/object/area.py
structengpy/app/general/object/frame.py
structengpy/app/general/object/joint.py
structengpy/app/general/post/__init__.py
structengpy/app/general/post/combination.py
structengpy/app/general/property/__init__.py
structengpy/app/general/property/area_section.py
structengpy/app/general/property/frame_section.py
structengpy/app/general/property/material.py
structengpy/app/general/result/__init__.py
structengpy/app/general/result/result.py
structengpy/app/general/solve/__init__.py
structengpy/common/__init__.py
structengpy/common/csys.py
structengpy/common/curve.py
structengpy/common/logger.py
structengpy/common/tolerance.py
structengpy/core/__init__.py
structengpy/core/fe_model/__init__.py
structengpy/core/fe_model/assembly.py
structengpy/core/fe_model/model.py
structengpy/core/fe_model/node.py
structengpy/core/fe_model/element/__init__.py
structengpy/core/fe_model/element/line/__init__.py
structengpy/core/fe_model/element/line/beam.py
structengpy/core/fe_model/element/line/link.py
structengpy/core/fe_model/element/quad/__init__.py
structengpy/core/fe_model/element/quad/membrane.py
structengpy/core/fe_model/element/quad/plate.py
structengpy/core/fe_model/element/tri/__init__.py
structengpy/core/fe_model/element/tri/membrane.py
structengpy/core/fe_model/load/__init__.py
structengpy/core/fe_model/load/loadcase.py
StructEngPy-0.1.14.dist-info/LICENSE
StructEngPy-0.1.14.dist-info/METADATA
StructEngPy-0.1.14.dist-info/WHEEL
StructEngPy-0.1.14.dist-info/top_level.txt
StructEngPy-0.1.14.dist-info/RECORD
